{"name":"interactiveworks","className":"ModuleScript","filePaths":["lib\\init.luau","default.project.json"],"children":[{"name":"util","className":"Folder","children":[{"name":"bindable","className":"ModuleScript","filePaths":["lib\\util\\bindable.luau"]},{"name":"utility","className":"ModuleScript","filePaths":["lib\\util\\utility.luau"]}]},{"name":"interactive","className":"ModuleScript","filePaths":["lib\\interactive.luau"]},{"name":"modding","className":"ModuleScript","filePaths":["lib\\modding.luau"]},{"name":"singleton","className":"ModuleScript","filePaths":["lib\\singleton.luau"]}]}